<pokedex>
    <pokemon id="45">
        <name>VILEPLUME</name>
        <type>Grass</type>
        <type>Poison</type>
        <ability>Chlorophyll</ability>
        <exp>1059860</exp>
        <stats>
            <HP>75</HP>
            <ATK>80</ATK>
            <DEF>85</DEF>
            <SPD>50</SPD>
            <SAT>100</SAT>
            <SDF>90</SDF>
        </stats>
        <evolutions>
            <evolution id="43">
                <name>Oddish</name>
            </evolution>
            <evolution id="44">
                <name>Gloom</name>
                <lvl>21</lvl>
            </evolution>
            <evolution id="182">
                <name>Bellossom</name>
                <condition>Sun Stone</condition>
            </evolution>
            <evolution id="45">
                <name>Vileplume</name>
                <condition>Leaf Stone</condition>
            </evolution>
        </evolutions>
        <egg-group>Grass</egg-group>
        <species>Flower Pokemon</species>
        <height>1.2</height>
        <weight>18.6</weight>
        <description>Its petals are the largest in the world. As it walks, it scatters extremely allergenic pollen.</description>
        <moves>
            <move type="level-up">
                <name>Mega Drain</name>
                <lvl>1</lvl>
            </move>
            <move type="level-up">
                <name>Aromatherapy</name>
                <lvl>1</lvl>
            </move>
            <move type="level-up">
                <name>Stun Spore</name>
                <lvl>1</lvl>
            </move>
            <move type="level-up">
                <name>Poisonpowder</name>
                <lvl>1</lvl>
            </move>
            <move type="level-up">
                <name>Petal Dance</name>
                <lvl>53</lvl>
            </move>
            <move type="level-up">
                <name>Solarbeam</name>
                <lvl>65</lvl>
            </move>
            <move type="TM/HM">
                <machine>TM</machine>
                <name>Toxic</name>
                <lvl>06</lvl>
            </move>
            <move type="TM/HM">
                <machine>TM</machine>
                <name>Bullet Seed</name>
                <lvl>09</lvl>
            </move>
            <move type="TM/HM">
                <machine>TM</machine>
                <name>Hidden Power</name>
                <lvl>10</lvl>
            </move>
            <move type="TM/HM">
                <machine>TM</machine>
                <name>Sunny Day</name>
                <lvl>11</lvl>
            </move>
            <move type="TM/HM">
                <machine>TM</machine>
                <name>Hyper Beam</name>
                <lvl>15</lvl>
            </move>
            <move type="TM/HM">
                <machine>TM</machine>
                <name>Protect</name>
                <lvl>17</lvl>
            </move>
            <move type="TM/HM">
                <machine>TM</machine>
                <name>Giga Drain</name>
                <lvl>19</lvl>
            </move>
            <move type="TM/HM">
                <machine>TM</machine>
                <name>Frustration</name>
                <lvl>21</lvl>
            </move>
            <move type="TM/HM">
                <machine>TM</machine>
                <name>Solarbeam</name>
                <lvl>22</lvl>
            </move>
            <move type="TM/HM">
                <machine>TM</machine>
                <name>Return</name>
                <lvl>27</lvl>
            </move>
            <move type="TM/HM">
                <machine>TM</machine>
                <name>Double Team</name>
                <lvl>32</lvl>
            </move>
            <move type="TM/HM">
                <machine>TM</machine>
                <name>Sludge Bomb</name>
                <lvl>36</lvl>
            </move>
            <move type="TM/HM">
                <machine>TM</machine>
                <name>Facade</name>
                <lvl>42</lvl>
            </move>
            <move type="TM/HM">
                <machine>TM</machine>
                <name>Secret Power</name>
                <lvl>43</lvl>
            </move>
            <move type="TM/HM">
                <machine>TM</machine>
                <name>Rest</name>
                <lvl>44</lvl>
            </move>
            <move type="TM/HM">
                <machine>TM</machine>
                <name>Attract</name>
                <lvl>45</lvl>
            </move>
            <move type="TM/HM">
                <machine>TM</machine>
                <name>Energy Ball</name>
                <lvl>53</lvl>
            </move>
            <move type="TM/HM">
                <machine>TM</machine>
                <name>Fling</name>
                <lvl>56</lvl>
            </move>
            <move type="TM/HM">
                <machine>TM</machine>
                <name>Endure</name>
                <lvl>58</lvl>
            </move>
            <move type="TM/HM">
                <machine>TM</machine>
                <name>Drain Punch</name>
                <lvl>60</lvl>
            </move>
            <move type="TM/HM">
                <machine>TM</machine>
                <name>Giga Impact</name>
                <lvl>68</lvl>
            </move>
            <move type="TM/HM">
                <machine>TM</machine>
                <name>Flash</name>
                <lvl>70</lvl>
            </move>
            <move type="TM/HM">
                <machine>TM</machine>
                <name>Swords Dance</name>
                <lvl>75</lvl>
            </move>
            <move type="TM/HM">
                <machine>TM</machine>
                <name>Captivate</name>
                <lvl>78</lvl>
            </move>
            <move type="TM/HM">
                <machine>TM</machine>
                <name>Sleep Talk</name>
                <lvl>82</lvl>
            </move>
            <move type="TM/HM">
                <machine>TM</machine>
                <name>Natural Gift</name>
                <lvl>83</lvl>
            </move>
            <move type="TM/HM">
                <machine>TM</machine>
                <name>Grass Knot</name>
                <lvl>86</lvl>
            </move>
            <move type="TM/HM">
                <machine>TM</machine>
                <name>Swagger</name>
                <lvl>87</lvl>
            </move>
            <move type="TM/HM">
                <machine>TM</machine>
                <name>Substitute</name>
                <lvl>90</lvl>
            </move>
            <move type="TM/HM">
                <machine>HM</machine>
                <name>Cut</name>
                <lvl>1</lvl>
            </move>
        </moves>
    </pokemon>
    </pokedex>